LambdaPage/LambdaPage.py
LambdaPage/__init__.py
LambdaPage-0.0.12.dist-info/LICENSE
LambdaPage-0.0.12.dist-info/METADATA
LambdaPage-0.0.12.dist-info/WHEEL
LambdaPage-0.0.12.dist-info/top_level.txt
LambdaPage-0.0.12.dist-info/RECORD
