Metadata-Version: 2.1
Name: LambdaPage
Version: 0.0.12
Summary: Python library for creating, testing, and deploying small single-page web applications using AWS Lambda and API-Gateway
Home-page: https://github.com/pentairiot/LambdaPage
Author: PentairIoT
Author-email: pentairiot@gmail.com
License: UNKNOWN
Platform: UNKNOWN
Classifier: Programming Language :: Python :: 3
Classifier: License :: OSI Approved :: MIT License
Classifier: Operating System :: OS Independent
Requires-Dist: pytz
Provides-Extra: aws
Requires-Dist: boto3 ; extra == 'aws'
Provides-Extra: local
Requires-Dist: falcon ; extra == 'local'
